SouBaiduPan/__init__.py
SouBaiduPan/searcher.py
SouBaiduPan/thread_tools.py
SouBaiduPan-0.1.5.dist-info/LICENSE
SouBaiduPan-0.1.5.dist-info/METADATA
SouBaiduPan-0.1.5.dist-info/WHEEL
SouBaiduPan-0.1.5.dist-info/top_level.txt
SouBaiduPan-0.1.5.dist-info/RECORD
